Workbook

Sheet 0_はじめに
A1: ねここち FC実証記録シート
A2: 1号店（町田店）— FCパッケージのための記録
B5: このシートの目的 | C5: 1号店は FCパッケージの実証実験です。他店に転用できる数字と手順を残すことが目的です。
C6: 予想収益を示してFCを募集するには、公正取引委員会のガイドライン上、算定根拠の開示が必要です。
C7: つまり、この記録がないとFCの募集自体ができません。
B9: いちばん大事な列 | C9: 「差の理由」と「所要時間」。金額そのものより、なぜそうなったかが他店に効きます。
B11: シートの構成 | C11: ① 初期投資 発生の都度。実額と、FC標準モデルの相場を並べる
C12: ② 月次記録 毎月1行。締めたその日に入れる
C13: ③ 一時イベント 発生の都度。採用・教育・保健所・クレーム・設備・集客
C14: ④ 定性・要件 随時。物件要件・設備・仕入先・掲載文・スクリプト
C15: ⑤ 標準モデル 会員数を入れると、加盟店に見せる損益が出ます（入力は黄色セルのみ）
B17: 記入のルール | C17: ・黄色のセルだけ入力してください。それ以外は計算式が入っています
C18: ・各シートの2行目に、書き方の例を1行入れてあります。上書きせず、3行目から追加してください
C19: ・「あとでまとめる」はできません。その日のうちに埋める運用にしてください
B21: 前提の数字 | C21: 会員1人あたり月次売上 6,636円／ロイヤリティ 売上の5%（いずれも⑤で変更できます）
C22: 1号店の家賃は0円（自宅1階）。FC標準モデルでは月150,000円として計上します
B24: 作成 | C24: 2026-09-03 ／ 企画書『町田Wブランド企画書』9-12 に対応

Sheet 1_初期投資
A1: ① 初期投資
A2: 実額と FC標準モデルの相場を並べる。「差の理由」がいちばん重要です
A4: 項目 | B4: 1号店の実額 | C4: 領収書No. | D4: 支払日 | E4: FC標準モデル | F4: 差額 | G4: 差の理由 | H4: 備考
A5: 【例】内装工事 | B5: 0 | C5: — | D5: 2026-08-31 | E5: 3000000 | F5: =E5-B5 | G5: 入居前に完了済み。1号店だけの特殊条件 | H5: 相場は200〜500万円
A6: 加盟金 | E6: 1500000 | F6: =E6-B6 | G6: 実証店として免除（FC契約に明記） | H6: 他店は100〜150万円。モデルは上限で置く
A7: 研修費 | E7: 300000 | F7: =E7-B7 | G7: 実証店として免除
A8: 内装工事 | E8: 3000000 | F8: =E8-B8 | H8: 施術室2室・待合・専用出入口
A9: 敷金・保証金 | E9: 900000 | F9: =E9-B9 | G9: 自宅のため不要 | H9: 家賃6ヶ月分
A10: 什器・備品 | E10: 500000 | F10: =E10-B10 | H10: ★1号店の実額を必ず入れること
A11: 鍼・消耗品（初回） | F11: =E11-B11 | H11: 型番と仕入先は④へ
A12: 予約・決済システム 初期 | F12: =E12-B12
A13: 看板・サイン | F13: =E13-B13
A14: HPB 初期費用 | F14: =E14-B14
A15: 運転資金 | E15: 3000000 | F15: =E15-B15 | H15: 1号店は100〜150万円
A16: その他 | F16: =E16-B16
A17: 合計 | B17: =SUM(B6:B16) | E17: =SUM(E6:E16) | F17: =SUM(F6:F16)
A19: 黄色のセルに入力してください。F列（差額）は自動計算です。
A20: 5行目は記入例です。上書きせず、6行目以降に実額を入れてください。
A21: 合計は例の行を除いた6行目以降の合計です。

Sheet 2_月次記録
A1: ② 月次記録
A2: 毎月1行。締めたその日に。実キャッシュ損益と標準モデル損益を両方見ます
A4: 年月 | B4: 月1会員 | C4: 月2会員 | D4: 都度 利用 | E4: 新規 初回 | F4: 会員化 | G4: 解約 | H4: 売上 | I4: 人件費 | J4: HPB | K4: その他 経費 | L4: ロイヤ リティ | M4: 実キャッシュ 損益 | N4: 内部保留 家賃 | O4: 標準モデル 損益 | P4: 施術 回数 | Q4: 稼働率
A5: 2026-12 | B5: 20 | C5: 0 | D5: 3 | E5: 25 | F5: 8 | G5: 0 | H5: 131000 | I5: 350000 | J5: 50000 | K5: 100000 | L5: =ROUND(H5*'5_標準モデル'!$B$4,0) | M5: =H5-I5-J5-K5-L5 | N5: ='5_標準モデル'!$B$5 | O5: =M5-N5 | P5: 26 | Q5: =IFERROR(P5/'5_標準モデル'!$B$6,0)
L6: =IF(H6="","",ROUND(H6*'5_標準モデル'!$B$4,0)) | M6: =IF(H6="","",H6-I6-J6-K6-L6) | N6: =IF(H6="","",'5_標準モデル'!$B$5) | O6: =IF(H6="","",M6-N6) | Q6: =IFERROR(P6/'5_標準モデル'!$B$6,"")
L7: =IF(H7="","",ROUND(H7*'5_標準モデル'!$B$4,0)) | M7: =IF(H7="","",H7-I7-J7-K7-L7) | N7: =IF(H7="","",'5_標準モデル'!$B$5) | O7: =IF(H7="","",M7-N7) | Q7: =IFERROR(P7/'5_標準モデル'!$B$6,"")
L8: =IF(H8="","",ROUND(H8*'5_標準モデル'!$B$4,0)) | M8: =IF(H8="","",H8-I8-J8-K8-L8) | N8: =IF(H8="","",'5_標準モデル'!$B$5) | O8: =IF(H8="","",M8-N8) | Q8: =IFERROR(P8/'5_標準モデル'!$B$6,"")
L9: =IF(H9="","",ROUND(H9*'5_標準モデル'!$B$4,0)) | M9: =IF(H9="","",H9-I9-J9-K9-L9) | N9: =IF(H9="","",'5_標準モデル'!$B$5) | O9: =IF(H9="","",M9-N9) | Q9: =IFERROR(P9/'5_標準モデル'!$B$6,"")
L10: =IF(H10="","",ROUND(H10*'5_標準モデル'!$B$4,0)) | M10: =IF(H10="","",H10-I10-J10-K10-L10) | N10: =IF(H10="","",'5_標準モデル'!$B$5) | O10: =IF(H10="","",M10-N10) | Q10: =IFERROR(P10/'5_標準モデル'!$B$6,"")
L11: =IF(H11="","",ROUND(H11*'5_標準モデル'!$B$4,0)) | M11: =IF(H11="","",H11-I11-J11-K11-L11) | N11: =IF(H11="","",'5_標準モデル'!$B$5) | O11: =IF(H11="","",M11-N11) | Q11: =IFERROR(P11/'5_標準モデル'!$B$6,"")
L12: =IF(H12="","",ROUND(H12*'5_標準モデル'!$B$4,0)) | M12: =IF(H12="","",H12-I12-J12-K12-L12) | N12: =IF(H12="","",'5_標準モデル'!$B$5) | O12: =IF(H12="","",M12-N12) | Q12: =IFERROR(P12/'5_標準モデル'!$B$6,"")
L13: =IF(H13="","",ROUND(H13*'5_標準モデル'!$B$4,0)) | M13: =IF(H13="","",H13-I13-J13-K13-L13) | N13: =IF(H13="","",'5_標準モデル'!$B$5) | O13: =IF(H13="","",M13-N13) | Q13: =IFERROR(P13/'5_標準モデル'!$B$6,"")
L14: =IF(H14="","",ROUND(H14*'5_標準モデル'!$B$4,0)) | M14: =IF(H14="","",H14-I14-J14-K14-L14) | N14: =IF(H14="","",'5_標準モデル'!$B$5) | O14: =IF(H14="","",M14-N14) | Q14: =IFERROR(P14/'5_標準モデル'!$B$6,"")
L15: =IF(H15="","",ROUND(H15*'5_標準モデル'!$B$4,0)) | M15: =IF(H15="","",H15-I15-J15-K15-L15) | N15: =IF(H15="","",'5_標準モデル'!$B$5) | O15: =IF(H15="","",M15-N15) | Q15: =IFERROR(P15/'5_標準モデル'!$B$6,"")
L16: =IF(H16="","",ROUND(H16*'5_標準モデル'!$B$4,0)) | M16: =IF(H16="","",H16-I16-J16-K16-L16) | N16: =IF(H16="","",'5_標準モデル'!$B$5) | O16: =IF(H16="","",M16-N16) | Q16: =IFERROR(P16/'5_標準モデル'!$B$6,"")
L17: =IF(H17="","",ROUND(H17*'5_標準モデル'!$B$4,0)) | M17: =IF(H17="","",H17-I17-J17-K17-L17) | N17: =IF(H17="","",'5_標準モデル'!$B$5) | O17: =IF(H17="","",M17-N17) | Q17: =IFERROR(P17/'5_標準モデル'!$B$6,"")
... L29: =IF(H29="","",ROUND(H29*'5_標準モデル'!$B$4,0)) | M29: =IF(H29="","",H29-I29-J29-K29-L29) | N29: =IF(H29="","",'5_標準モデル'!$B$5) | O29: =IF(H29="","",M29-N29) | Q29: =IFERROR(P29/'5_標準モデル'!$B$6,"")
A31: 黄色＝入力。L〜O列・Q列は自動計算です。
A32: 実キャッシュ損益＝資金が持つかを見る数字。標準モデル損益＝加盟店に見せられる数字（家賃15万を引いた後）。
A33: 稼働率＝施術回数 ÷ 月間キャパ（⑤で設定）。
A34: 5行目は記入例です。6行目以降に実績を入れてください。

Sheet 3_一時イベント
A1: ③ 一時イベント記録
A2: 採用・教育・保健所・クレーム・設備・集客。所要時間を必ず入れてください
A4: 日付 | B4: 種別 | C4: 内容 | D4: 所要時間 (h) | E4: 費用 | F4: 結果・数値 | G4: 次回への申し送り
A5: 2026-11-10 | B5: 採用 | C5: 求人掲載〜内定（鍼灸師1名） | D5: 32 | E5: 80000 | F5: 応募12名／面接4名／内定1名 | G5: 社保完備の記載で応募が倍増。掲載は月初が反応良い
A47: 種別は6つから選んでください：採用／教育／保健所・行政／クレーム・ヒヤリハット／設備・仕入／集客施策
A48: 「所要時間」が最重要です。加盟店にとって最大のコストは、お金ではなくオーナーの時間です。
A49: 「開業前の準備に何時間かかるか」を示せるFC本部は、ほとんどありません。

Sheet 4_定性・要件
A1: ④ 定性・要件記録
A2: そのままFCパッケージの中身になります
A4: カテゴリ | B4: 項目 | C4: 内容 | D4: FCパッケージへの反映先 | E4: 更新日
A5: 【例】物件要件 | B5: 施術室の広さ | C5: 6.6㎡以上／2室（ここちめいどと並行運用するため） | D5: 物件選定チェックリスト | E5: 2026-09-03
A6: 物件要件 | B6: 待合室 | D6: 物件選定チェックリスト
A7: 物件要件 | B7: 専用出入口・動線 | D7: 物件選定チェックリスト
A8: 物件要件 | B8: 立地条件（駅からの距離・視認性） | D8: 物件選定チェックリスト
A9: 設備 | B9: ベッド・什器の型番と仕入先 | D9: 開業備品リスト
A10: 設備 | B10: 消毒・洗浄設備 | D10: 衛生マニュアル
A11: 仕入 | B11: 鍼の型番・単価・仕入先 | D11: 物品供給リスト
A12: 仕入 | B12: 医療廃棄物の委託先・費用 | D12: 衛生マニュアル
A13: 行政 | B13: 保健所への届出手順（提出書類・期間） | D13: 開業手続き手順書
A14: 行政 | B14: 任意包括適用の手続き（期間・書類） | D14: 労務手順書
A15: 集客 | B15: HPB掲載文（本文） | D15: 集客マニュアル
A16: 集客 | B16: HPB写真の構成と反応 | D16: 集客マニュアル
A17: 集客 | B17: クーポン設計と転換率 | D17: 集客マニュアル
... A23: 運営 | B23: 2人目を雇うタイミングの判断基準 | D23: 店舗運営マニュアル
A37: C列（内容）とE列（更新日）が入力欄です。行は自由に足してください。
A38: D列は、その記録がFCパッケージのどの文書になるかを示しています。

Sheet 5_標準モデル
A1: ⑤ FC標準モデル
A2: 会員数を入れると、加盟店に見せる損益が出ます
A3: ■ 前提（黄色＝変更できます）
A4: ロイヤリティ率 | B4: 0.05 | C4: 売上に対する率。1号店にも他店と同率を適用します
A5: 家賃（標準モデル） | B5: 150000 | C5: 1号店は0円。他店では月15万円かかります
A6: 月間キャパ（施術回数） | B6: 220 | C6: 1名・稼働率60%想定。②の稼働率計算に使います
A7: 会員1人あたり月次売上 | B7: 6636 | C7: 月1会員150人＋月2会員50人＋都度20人のミックス
A8: 人件費（月給＋社保） | B8: 350000 | C8: 月給30万＋社会保険 会社負担 約15%
A9: HPB掲載費 | B9: 50000
A10: 水道光熱・消耗品・システム・保険 | B10: 100000
A12: ■ 会員数を入れてください
A13: 会員数 | B13: 150 | C13: ここを変えると下がすべて動きます
A15: ■ FC標準モデル（加盟店に見せる数字）
A16: 売上 | B16: =B13*B7 | C16: 会員数 × 1人あたり月次売上
A17: 人件費 | B17: =-B8
A18: 家賃 | B18: =-B5 | C18: ★1号店では発生しないが、他店では必ずかかる
A19: HPB掲載費 | B19: =-B9
A20: 水道光熱・消耗品・システム | B20: =-B10
A21: ロイヤリティ | B21: =-ROUND(B16*B4,0)
A22: 加盟店の利益 | B22: =SUM(B16:B21)
A23: 損益分岐 会員数 | B23: =ROUND((B8+B5+B9+B10)/(1-B4)/B7,1) | C23: 加盟店が再現できるライン
A25: ■ 1号店の実際（家賃ゼロ）
A26: 売上 | B26: =B13*B7
A27: 固定費（人件費＋HPB＋その他） | B27: =-(B8+B9+B10) | C27: 家賃は入らない
A28: ロイヤリティ | B28: =-ROUND(B26*B4,0)
A29: 1号店の利益 | B29: =B26+B27+B28
A30: 損益分岐 会員数 | B30: =ROUND((B8+B9+B10)/(1-B4)/B7,1) | C30: 資金が尽きないライン
A31: 差（内部保留すべき家賃） | B31: =B29-B22 | C31: ★この額が「見かけ上の余裕」です
A33: ■ 投資回収（標準モデル）
A34: 初期投資 | B34: ='1_初期投資'!E17 | C34: ①の標準モデル合計から自動参照
A35: 月利益 | B35: =B22
A36: 単純回収（ヶ月） | B36: =IFERROR(B34/B35,0)
A37: 黒字化までの月数 | B37: 6 | C37: 会員が損益分岐に達するまで
A38: 実質回収（ヶ月） | B38: =B36+B37 | C38: 目標は30ヶ月以内
A40: 黄色のセルだけ変更してください。それ以外は計算式です。
A41: B34（初期投資）は「1_初期投資」シートのE列合計を参照しています。
A42: 1号店の利益と標準モデルの利益の差（B31）が、内部保留すべき家賃です。この額を「儲かっている」と誤解しないこと。
